MsgJimPyServer-1.2.1.data/scripts/server_run
server/__init__.py
server/server.ini
server/server.py
server/server_run
server/common/__init__.py
server/common/descriptors.py
server/common/errors.py
server/common/metaclasses.py
server/common/proj_decorators.py
server/common/utils.py
server/common/variables.py
server/server/__init__.py
server/server/add_user.py
server/server/config_window.py
server/server/core.py
server/server/main_window.py
server/server/remove_user.py
server/server/server_db.py
server/server/stat_window.py
server/server/logs/__init__.py
server/server/logs/server_log_config.py
server/unit_tests/__init__.py
server/unit_tests/test_utils.py
MsgJimPyServer-1.2.1.dist-info/METADATA
MsgJimPyServer-1.2.1.dist-info/WHEEL
MsgJimPyServer-1.2.1.dist-info/top_level.txt
MsgJimPyServer-1.2.1.dist-info/RECORD
