Metadata-Version: 2.1
Name: MsgJimPyServer
Version: 1.2.1
Summary: Server part of jim based messenger 
Author: Roman Lopatin
Author-email: romanlopatin@gmail.com
Requires-Dist: PyQt5
Requires-Dist: sqlalchemy
